istonaoexiste-0.1.0.dist-info/licenses/license
minha_biblioteca/__init__.py
minha_biblioteca/exemplo.py
istonaoexiste-0.1.0.dist-info/METADATA
istonaoexiste-0.1.0.dist-info/WHEEL
istonaoexiste-0.1.0.dist-info/top_level.txt
istonaoexiste-0.1.0.dist-info/RECORD
