Metadata-Version: 2.4
Name: istonaoexiste
Version: 0.1.0
Summary: Uma biblioteca de exemplo criada no curso
Author-email: Nome <nome@email.com>
License: MIT
Requires-Python: >=3.8
License-File: license
Dynamic: license-file
